Metadata-Version: 1.1
Name: django-rest-tables
Version: 0.1.0
Summary: Package description
